[
  {
    "type": "Snack",
    "name": "Multi Grain Combo Cookies",
    "rating": 0,
    "previousPrice": 30,
    "discountPrice": 25,
    "time": "new",
    "weight": 2,
    "image": "https://maraviyainfotech.com/projects/grabit-tailwind/grabit-tailwind/assets/img/product-images/3_1.jpg",
    "id": "1",
    "count": 0
  },
  {
    "type": "Fruits",
    "name": "Mixed Nuts Berries Pack",
    "rating": 5,
    "previousPrice": 56,
    "discountPrice": 45,
    "time": "old",
    "weight": 1,
    "image": "https://maraviyainfotech.com/projects/grabit-tailwind/grabit-tailwind/assets/img/product-images/6_1.jpg",
    "id": "2",
    "count": 0
  },
  {
    "type": "Juice",
    "name": "Fresh Mango Juice Pack",
    "rating": 0,
    "previousPrice": 65,
    "discountPrice": 49,
    "time": "old",
    "weight": 3,
    "image": "https://maraviyainfotech.com/projects/grabit-tailwind/grabit-tailwind/assets/img/product-images/9_1.jpg",
    "id": "3",
    "count": 0
  },
  {
    "type": "Fruits",
    "name": "Dates Value Fresh Pouch",
    "rating": 0,
    "previousPrice": 56,
    "discountPrice": 45,
    "time": "old",
    "weight": 4,
    "image": "https://maraviyainfotech.com/projects/grabit-tailwind/grabit-tailwind/assets/img/product-images/2_1.jpg",
    "id": "4",
    "count": 0
  },
  {
    "type": "Bakery",
    "name": "Stick Fiber Masala Magic",
    "rating": 0,
    "previousPrice": 50,
    "discountPrice": 45,
    "time": "old",
    "weight": 1,
    "image": "https://maraviyainfotech.com/projects/grabit-tailwind/grabit-tailwind/assets/img/product-images/1_1.jpg",
    "id": "5",
    "count": 0
  },
  {
    "type": "Vegetables",
    "name": "Fresh Organic Ginger Pack",
    "rating": 0,
    "previousPrice": 3,
    "discountPrice": 2,
    "time": "old",
    "weight": 2,
    "image": "https://maraviyainfotech.com/projects/grabit-tailwind/grabit-tailwind/assets/img/product-images/17_1.jpg",
    "id": "6",
    "count": 0
  },
  {
    "type": "Fruits",
    "name": "Natural Hub Cherry Karonda",
    "rating": 0,
    "previousPrice": 56,
    "discountPrice": 45,
    "time": "old",
    "weight": 4,
    "image": "https://maraviyainfotech.com/projects/grabit-tailwind/grabit-tailwind/assets/img/product-images/24_1.jpg",
    "id": "7",
    "count": 0
  },
  {
    "type": "Fruits",
    "name": "Fresh Lichi 500g Pack",
    "rating": 0,
    "previousPrice": 35,
    "discountPrice": 25,
    "time": "new",
    "weight": 3,
    "image": "https://maraviyainfotech.com/projects/grabit-tailwind/grabit-tailwind/assets/img/product-images/24_1.jpg",
    "id": "8",
    "count": 0
  },
  {
    "type": "Snack",
    "name": "Smoked Honey Spiced Nuts Almonds Pack",
    "rating": 0,
    "previousPrice": 56,
    "discountPrice": 45,
    "time": "new",
    "weight": 5,
    "image": "https://maraviyainfotech.com/projects/grabit-tailwind/grabit-tailwind/assets/img/product-images/8_1.jpg",
    "id": "9",
    "count": 0
  },
  {
    "type": "Fruits",
    "name": "Banana Chips Snack Crunchy",
    "rating": 0,
    "previousPrice": 50,
    "discountPrice": 45,
    "weight": 7,
    "time": "old",
    "image": "https://maraviyainfotech.com/projects/grabit-tailwind/grabit-tailwind/assets/img/product-images/4_1.jpg",
    "id": "10",
    "count": 0
  },
  {
    "type": "Bakery",
    "name": "Mixed Nuts & Almonds Dry Fruits",
    "rating": 0,
    "previousPrice": 65,
    "discountPrice": 49,
    "weight": 9,
    "time": "old",
    "image": "https://maraviyainfotech.com/projects/grabit-tailwind/grabit-tailwind/assets/img/product-images/9_1.jpg",
    "id": "11",
    "count": 0
  },
  {
    "type": "Dairy",
    "name": "Farm Eggs",
    "rating": 0,
    "previousPrice": 5,
    "discountPrice": 3,
    "weight": 7,
    "time": "old",
    "image": "https://maraviyainfotech.com/projects/grabit-tailwind/grabit-tailwind/assets/img/product-images/19_1.jpg",
    "id": "12",
    "count": 0
  },
  {
    "type": "Dairy",
    "name": "Carrot & Brocoli Soup Mix Pack",
    "rating": 0,
    "previousPrice": 35,
    "discountPrice": 25,
    "weight": 2,
    "time": "new",
    "image": "https://maraviyainfotech.com/projects/grabit-tailwind/grabit-tailwind/assets/img/product-images/5_1.jpg",
    "id": "13",
    "count": 0
  },
  {
    "type": "Vegetables",
    "name": "Ginger Organic",
    "rating": 0,
    "previousPrice": 56,
    "discountPrice": 45,
    "weight": 4,
    "time": "old",
    "image": "https://maraviyainfotech.com/projects/grabit-tailwind/grabit-tailwind/assets/img/product-images/17_1.jpg",
    "id": "14",
    "count": 0
  },
  {
    "type": "Fruits",
    "name": "Healthy Nutmix",
    "rating": 0,
    "previousPrice": 45,
    "discountPrice": 42,
    "weight": 5,
    "time": "new",
    "image": "https://maraviyainfotech.com/projects/grabit-tailwind/grabit-tailwind/assets/img/product-images/10_1.jpg",
    "id": "15",
    "count": 0
  },
  {
    "type": "Fruits",
    "name": "organic Fresh Tomato",
    "rating": 0,
    "previousPrice": 30,
    "discountPrice": 25,
    "weight": 2,
    "time": "new",
    "image": "https://maraviyainfotech.com/projects/grabit-tailwind/grabit-tailwind/assets/img/product-images/11_1.jpg",
    "id": "16",
    "count": 0
  }
]